TPWUtils/Credentials.py
TPWUtils/GreatCircle.py
TPWUtils/INotify.py
TPWUtils/Logger.py
TPWUtils/SingleInstance.py
TPWUtils/Thread.py
TPWUtils/__init__.py
TPWUtils/install.py
TPWUtils/loadAndExecuteSQL.py
tpwutils-0.2.0.dist-info/licenses/LICENSE
tpwutils-0.2.0.dist-info/METADATA
tpwutils-0.2.0.dist-info/WHEEL
tpwutils-0.2.0.dist-info/top_level.txt
tpwutils-0.2.0.dist-info/RECORD
