Metadata-Version: 2.4
Name: TPWUtils
Version: 0.2.0
Summary: A collection of Python 3 utilities for logging, threading, file monitoring, and geographic calculations
Author-email: Pat Welch <pat@mousebrains.com>
License-Expression: GPL-3.0-or-later
Project-URL: Homepage, https://github.com/mousebrains/TPWUtils
Project-URL: Repository, https://github.com/mousebrains/TPWUtils
Project-URL: Issues, https://github.com/mousebrains/TPWUtils/issues
Keywords: logging,threading,inotify,great-circle,credentials,systemd
Classifier: Development Status :: 4 - Beta
Classifier: Intended Audience :: Developers
Classifier: Operating System :: POSIX :: Linux
Classifier: Operating System :: MacOS
Classifier: Programming Language :: Python :: 3
Classifier: Programming Language :: Python :: 3.10
Classifier: Programming Language :: Python :: 3.11
Classifier: Programming Language :: Python :: 3.12
Classifier: Programming Language :: Python :: 3 :: Only
Classifier: Topic :: Software Development :: Libraries :: Python Modules
Classifier: Topic :: System :: Logging
Classifier: Topic :: System :: Monitoring
Requires-Python: >=3.10
License-File: LICENSE
Requires-Dist: numpy
Requires-Dist: pyinotify; sys_platform == "linux"
Requires-Dist: pyyaml
Provides-Extra: dev
Requires-Dist: pytest; extra == "dev"
Requires-Dist: pytest-cov; extra == "dev"
Provides-Extra: database
Requires-Dist: psycopg>=3.0; extra == "database"
Provides-Extra: analysis
Requires-Dist: pandas; extra == "analysis"
Requires-Dist: xarray; extra == "analysis"
Dynamic: license-file
